capture/__init__.py
capture/client.py
capture_sdk-1.0.0.dist-info/METADATA
capture_sdk-1.0.0.dist-info/WHEEL
capture_sdk-1.0.0.dist-info/licenses/LICENSE
capture_sdk-1.0.0.dist-info/RECORD
