Metadata-Version: 2.4
Name: capture-sdk
Version: 1.0.0
Summary: Python SDK for Capture - Screenshot and content extraction API
Project-URL: Homepage, https://capture.page
Project-URL: Documentation, https://docs.capture.page
Project-URL: Repository, https://github.com/techulus/capture-py
Author-email: Capture Team <support@capture.page>
License: MIT
License-File: LICENSE
Keywords: capture,content extraction,pdf,screenshot,web scraping
Classifier: Development Status :: 4 - Beta
Classifier: Intended Audience :: Developers
Classifier: License :: OSI Approved :: MIT License
Classifier: Programming Language :: Python :: 3
Classifier: Programming Language :: Python :: 3.8
Classifier: Programming Language :: Python :: 3.9
Classifier: Programming Language :: Python :: 3.10
Classifier: Programming Language :: Python :: 3.11
Classifier: Programming Language :: Python :: 3.12
Classifier: Programming Language :: Python :: 3.13
Requires-Python: >=3.8
Requires-Dist: aiohttp>=3.8.0
Requires-Dist: yarl>=1.9.0
Provides-Extra: dev
Requires-Dist: black>=23.0.0; extra == 'dev'
Requires-Dist: mypy>=1.0.0; extra == 'dev'
Requires-Dist: pytest-asyncio>=0.21.0; extra == 'dev'
Requires-Dist: pytest>=7.0.0; extra == 'dev'
Requires-Dist: ruff>=0.1.0; extra == 'dev'
